{"latitude":39.952247,"longitude":-75.163894,"timezone":"America/New_York","offset":-4,"currently":{"time":931046400,"summary":"Clear","icon":"clear-day","precipIntensity":0,"precipProbability":0,"temperature":89.46,"apparentTemperature":100.09,"dewPoint":75.19,"humidity":0.63,"windSpeed":8.08,"windBearing":246,"visibility":7.05,"cloudCover":0.16,"pressure":1016.89},"hourly":{"summary":"Partly cloudy until later this evening.","icon":"partly-cloudy-day","data":[{"time":930974400,"summary":"Clear","icon":"clear-night","precipIntensity":0,"precipProbability":0,"temperature":72.71,"apparentTemperature":72.71,"dewPoint":70.98,"humidity":0.94,"windSpeed":3,"windBearing":250,"visibility":7.93,"cloudCover":0.16,"pressure":1019.49},{"time":930978000,"summary":"Partly Cloudy","icon":"partly-cloudy-night","precipIntensity":0,"precipProbability":0,"temperature":72.71,"apparentTemperature":72.71,"dewPoint":71.45,"humidity":0.96,"windSpeed":3,"windBearing":190,"visibility":7.95,"cloudCover":0.38,"pressure":1019.2},{"time":930981600,"summary":"Clear","icon":"clear-night","precipIntensity":0,"precipProbability":0,"temperature":72,"apparentTemperature":72,"dewPoint":70.49,"humidity":0.95,"windSpeed":6,"windBearing":180,"visibility":8.01,"cloudCover":0.16,"pressure":1018.49},{"time":930985200,"summary":"Clear","icon":"clear-night","precipIntensity":0,"precipProbability":0,"temperature":72,"apparentTemperature":72,"dewPoint":70.49,"humidity":0.95,"windSpeed":5.34,"windBearing":274,"visibility":6.79,"cloudCover":0.16,"pressure":1018.52},{"time":930988800,"summary":"Clear","icon":"clear-night","precipIntensity":0,"precipProbability":0,"temperature":72,"apparentTemperature":72,"dewPoint":71.11,"humidity":0.97,"windSpeed":3.5,"windBearing":196,"visibility":5.86,"cloudCover":0.16,"pressure":1018.15},{"time":930992400,"summary":"Mostly Cloudy","icon":"partly-cloudy-night","precipIntensity":0,"precipProbability":0,"temperature":72.09,"apparentTemperature":72.09,"dewPoint":71.49,"humidity":0.98,"windSpeed":3,"windBearing":250,"visibility":4.35,"cloudCover":0.66,"pressure":1019.21},{"time":930996000,"summary":"Overcast","icon":"cloudy","precipIntensity":0,"precipProbability":0,"temperature":72.38,"apparentTemperature":72.38,"dewPoint":72.12,"humidity":0.99,"windSpeed":4.08,"windBearing":310,"visibility":2,"cloudCover":1,"pressure":1019.87},{"time":930999600,"summary":"Mostly Cloudy","icon":"partly-cloudy-day","precipIntensity":0,"precipProbability":0,"temperature":73.51,"apparentTemperature":73.51,"dewPoint":72.86,"humidity":0.98,"windSpeed":4.98,"windBearing":276,"visibility":2.02,"cloudCover":0.6,"pressure":1020},{"time":931003200,"summary":"Foggy","icon":"fog","precipIntensity":0,"precipProbability":0,"temperature":75.57,"apparentTemperature":75.57,"dewPoint":73.66,"humidity":0.94,"windSpeed":3.94,"windBearing":306,"visibility":1.91,"cloudCover":0.86,"pressure":1020.16},{"time":931006800,"summary":"Mostly Cloudy","icon":"partly-cloudy-day","precipIntensity":0,"precipProbability":0,"temperature":77.49,"apparentTemperature":77.49,"dewPoint":73.14,"humidity":0.87,"windSpeed":3.54,"windBearing":282,"visibility":2.69,"cloudCover":0.82,"pressure":1020.74},{"time":931010400,"summary":"Partly Cloudy","icon":"partly-cloudy-day","precipIntensity":0,"precipProbability":0,"temperature":79.48,"apparentTemperature":79.48,"dewPoint":74.24,"humidity":0.84,"windSpeed":3.2,"windBearing":250,"visibility":3.48,"cloudCover":0.47,"pressure":1020.89},{"time":931014000,"summary":"Partly Cloudy","icon":"partly-cloudy-day","precipIntensity":0,"precipProbability":0,"temperature":81.01,"apparentTemperature":86.98,"dewPoint":75.25,"humidity":0.83,"windSpeed":8,"windBearing":200,"visibility":3.99,"cloudCover":0.33,"pressure":1021.6},{"time":931017600,"summary":"Partly Cloudy","icon":"partly-cloudy-day","precipIntensity":0,"precipProbability":0,"temperature":83.24,"apparentTemperature":91.22,"dewPoint":75.56,"humidity":0.78,"windSpeed":5.6,"windBearing":189,"visibility":4.4,"cloudCover":0.52,"pressure":1021.09},{"time":931021200,"summary":"Partly Cloudy","icon":"partly-cloudy-day","precipIntensity":0,"precipProbability":0,"temperature":85.17,"apparentTemperature":93.64,"dewPoint":74.84,"humidity":0.71,"windSpeed":5.69,"windBearing":244,"visibility":4.74,"cloudCover":0.26,"pressure":1020.62},{"time":931024800,"summary":"Partly Cloudy","icon":"partly-cloudy-day","precipIntensity":0,"precipProbability":0,"temperature":87.16,"apparentTemperature":95.32,"dewPoint":73.68,"humidity":0.64,"windSpeed":7.82,"windBearing":225,"visibility":5.33,"cloudCover":0.26,"pressure":1020.68},{"time":931028400,"summary":"Partly Cloudy","icon":"partly-cloudy-day","precipIntensity":0,"precipProbability":0,"temperature":89.16,"apparentTemperature":98.09,"dewPoint":73.78,"humidity":0.61,"windSpeed":7.92,"windBearing":226,"visibility":5.81,"cloudCover":0.26,"pressure":1020.68},{"time":931032000,"summary":"Partly Cloudy","icon":"partly-cloudy-day","precipIntensity":0,"precipProbability":0,"temperature":89.58,"apparentTemperature":98.11,"dewPoint":73.28,"humidity":0.59,"windSpeed":10,"windBearing":230,"visibility":5.81,"cloudCover":0.33,"pressure":1020.48},{"time":931035600,"summary":"Partly Cloudy","icon":"partly-cloudy-day","precipIntensity":0,"precipProbability":0,"temperature":90.49,"apparentTemperature":99.79,"dewPoint":73.74,"humidity":0.58,"windSpeed":6.08,"windBearing":224,"visibility":6.58,"cloudCover":0.25,"pressure":1019.8},{"time":931039200,"summary":"Clear","icon":"clear-day","precipIntensity":0,"precipProbability":0,"temperature":90.49,"apparentTemperature":99.15,"dewPoint":73.15,"humidity":0.57,"windSpeed":9,"windBearing":230,"visibility":6.57,"cloudCover":0.16,"pressure":1019.2},{"time":931042800,"summary":"Partly Cloudy","icon":"partly-cloudy-day","precipIntensity":0,"precipProbability":0,"temperature":89.08,"apparentTemperature":97.09,"dewPoint":72.91,"humidity":0.59,"windSpeed":6.21,"windBearing":219,"visibility":5.86,"cloudCover":0.25,"pressure":1018.85},{"time":931046400,"summary":"Clear","icon":"clear-day","precipIntensity":0,"precipProbability":0,"temperature":89.46,"apparentTemperature":100.09,"dewPoint":75.19,"humidity":0.63,"windSpeed":8.08,"windBearing":246,"visibility":7.05,"cloudCover":0.16,"pressure":1016.89},{"time":931050000,"summary":"Clear","icon":"clear-night","precipIntensity":0,"precipProbability":0,"temperature":84.73,"apparentTemperature":92.75,"dewPoint":74.59,"humidity":0.72,"windSpeed":8.69,"windBearing":214,"visibility":6.36,"cloudCover":0.16,"pressure":1019.59},{"time":931053600,"summary":"Clear","icon":"clear-night","precipIntensity":0,"precipProbability":0,"temperature":81.86,"apparentTemperature":88.82,"dewPoint":75.63,"humidity":0.82,"windSpeed":7.39,"windBearing":201,"visibility":6.08,"cloudCover":0.16,"pressure":1019.83},{"time":931057200,"summary":"Clear","icon":"clear-night","precipIntensity":0,"precipProbability":0,"temperature":80.36,"apparentTemperature":85.94,"dewPoint":75.58,"humidity":0.85,"windSpeed":7.54,"windBearing":192,"visibility":5.57,"cloudCover":0.16,"pressure":1019.61}]},"daily":{"data":[{"time":930974400,"summary":"Partly cloudy until evening.","icon":"partly-cloudy-day","sunriseTime":930994669,"sunsetTime":931048450,"moonPhase":0.65,"precipIntensity":0,"precipIntensityMax":0,"precipProbability":0,"temperatureMin":72,"temperatureMinTime":930988800,"temperatureMax":90.49,"temperatureMaxTime":931039200,"apparentTemperatureMin":72,"apparentTemperatureMinTime":930988800,"apparentTemperatureMax":99.15,"apparentTemperatureMaxTime":931039200,"dewPoint":73.3,"humidity":0.8,"windSpeed":5.04,"windBearing":228,"visibility":5.3,"cloudCover":0.36,"pressure":1019.74}]},"flags":{"sources":["isd"],"isd-stations":["724074-99999","724080-13739","724085-94732","724086-14793","725113-99999"],"units":"us"}}