{"latitude":39.952247,"longitude":-75.163894,"timezone":"America/New_York","offset":-4,"currently":{"time":1145145600,"summary":"Partly Cloudy","icon":"partly-cloudy-night","precipIntensity":0,"precipProbability":0,"temperature":66.11,"apparentTemperature":66.11,"dewPoint":31.06,"humidity":0.27,"windSpeed":5.61,"windBearing":349,"visibility":10,"cloudCover":0.29,"pressure":1004.4},"hourly":{"summary":"Partly cloudy until later this evening.","icon":"partly-cloudy-day","data":[{"time":1145073600,"summary":"Mostly Cloudy","icon":"partly-cloudy-night","precipIntensity":0,"precipProbability":0,"temperature":56.36,"apparentTemperature":56.36,"dewPoint":54,"humidity":0.92,"windSpeed":3,"windBearing":60,"visibility":4.72,"cloudCover":0.9,"pressure":1003.35},{"time":1145077200,"summary":"Overcast","icon":"cloudy","precipIntensity":0,"precipProbability":0,"temperature":54.94,"apparentTemperature":54.94,"dewPoint":52.48,"humidity":0.91,"visibility":3.71,"cloudCover":1,"pressure":1003.17},{"time":1145080800,"summary":"Mostly Cloudy","icon":"partly-cloudy-night","precipIntensity":0,"precipProbability":0,"temperature":54.46,"apparentTemperature":54.46,"dewPoint":53.01,"humidity":0.95,"windSpeed":0.86,"windBearing":10,"visibility":4.06,"cloudCover":0.68,"pressure":1002.51},{"time":1145084400,"summary":"Mostly Cloudy","icon":"partly-cloudy-night","precipIntensity":0,"precipProbability":0,"temperature":54.48,"apparentTemperature":54.48,"dewPoint":51.69,"humidity":0.9,"visibility":4.25,"cloudCover":0.67,"pressure":1001.68},{"time":1145088000,"summary":"Mostly Cloudy","icon":"partly-cloudy-night","precipIntensity":0,"precipProbability":0,"temperature":55.65,"apparentTemperature":55.65,"dewPoint":52.47,"humidity":0.89,"visibility":4.49,"cloudCover":0.75,"pressure":1001.2},{"time":1145091600,"summary":"Mostly Cloudy","icon":"partly-cloudy-night","precipIntensity":0,"precipProbability":0,"temperature":54.78,"apparentTemperature":54.78,"dewPoint":51.51,"humidity":0.89,"windSpeed":6,"windBearing":220,"visibility":4.95,"cloudCover":0.82,"pressure":1000.84},{"time":1145095200,"summary":"Partly Cloudy","icon":"partly-cloudy-night","precipIntensity":0,"precipProbability":0,"temperature":55.59,"apparentTemperature":55.59,"dewPoint":53.25,"humidity":0.92,"windSpeed":6.26,"windBearing":243,"visibility":4.92,"cloudCover":0.41,"pressure":1000.89},{"time":1145098800,"summary":"Partly Cloudy","icon":"partly-cloudy-day","precipIntensity":0.002,"precipProbability":0.2,"precipType":"rain","temperature":58.1,"apparentTemperature":58.1,"dewPoint":55.09,"humidity":0.9,"windSpeed":5.93,"windBearing":228,"visibility":6.84,"cloudCover":0.44,"pressure":1001.06},{"time":1145102400,"summary":"Partly Cloudy","icon":"partly-cloudy-day","precipIntensity":0,"precipProbability":0,"temperature":60.82,"apparentTemperature":60.82,"dewPoint":56.47,"humidity":0.86,"windSpeed":8.31,"windBearing":230,"visibility":7.43,"cloudCover":0.39,"pressure":1001.3},{"time":1145106000,"summary":"Partly Cloudy","icon":"partly-cloudy-day","precipIntensity":0,"precipProbability":0,"temperature":63.69,"apparentTemperature":63.69,"dewPoint":56.18,"humidity":0.77,"windSpeed":9.53,"windBearing":237,"visibility":10,"cloudCover":0.29,"pressure":1001.21},{"time":1145109600,"summary":"Partly Cloudy","icon":"partly-cloudy-day","precipIntensity":0,"precipProbability":0,"temperature":69.4,"apparentTemperature":69.4,"dewPoint":55.15,"humidity":0.61,"windSpeed":12.4,"windBearing":247,"visibility":10,"cloudCover":0.29,"pressure":1001.02},{"time":1145113200,"summary":"Partly Cloudy","icon":"partly-cloudy-day","precipIntensity":0,"precipProbability":0,"temperature":72.46,"apparentTemperature":72.46,"dewPoint":55.14,"humidity":0.55,"windSpeed":12.29,"windBearing":243,"visibility":10,"cloudCover":0.41,"pressure":1000.76},{"time":1145116800,"summary":"Partly Cloudy","icon":"partly-cloudy-day","precipIntensity":0,"precipProbability":0,"temperature":75.52,"apparentTemperature":75.52,"dewPoint":55.44,"humidity":0.5,"windSpeed":12.43,"windBearing":264,"visibility":10,"cloudCover":0.29,"pressure":1000.32},{"time":1145120400,"summary":"Partly Cloudy","icon":"partly-cloudy-day","precipIntensity":0,"precipProbability":0,"temperature":76.64,"apparentTemperature":76.64,"dewPoint":55.23,"humidity":0.48,"windSpeed":12.36,"windBearing":276,"visibility":10,"cloudCover":0.39,"pressure":999.49},{"time":1145124000,"summary":"Mostly Cloudy","icon":"partly-cloudy-day","precipIntensity":0,"precipProbability":0,"temperature":77.16,"apparentTemperature":77.16,"dewPoint":54.29,"humidity":0.45,"windSpeed":12.93,"windBearing":291,"visibility":10,"cloudCover":0.68,"pressure":999.16},{"time":1145127600,"summary":"Mostly Cloudy","icon":"partly-cloudy-day","precipIntensity":0,"precipProbability":0,"temperature":77.94,"apparentTemperature":77.94,"dewPoint":53.89,"humidity":0.43,"windSpeed":14.02,"windBearing":281,"visibility":10,"cloudCover":0.65,"pressure":998.73},{"time":1145131200,"summary":"Partly Cloudy","icon":"partly-cloudy-day","precipIntensity":0,"precipProbability":0,"temperature":78.71,"apparentTemperature":78.71,"dewPoint":52.75,"humidity":0.41,"windSpeed":14.97,"windBearing":281,"visibility":10,"cloudCover":0.44,"pressure":997.92},{"time":1145134800,"summary":"Partly Cloudy","icon":"partly-cloudy-day","precipIntensity":0,"precipProbability":0,"temperature":78.34,"apparentTemperature":78.34,"dewPoint":50.12,"humidity":0.37,"windSpeed":13.31,"windBearing":284,"visibility":10,"cloudCover":0.48,"pressure":997.85},{"time":1145138400,"summary":"Partly Cloudy","icon":"partly-cloudy-day","precipIntensity":0,"precipProbability":0,"temperature":77.12,"apparentTemperature":77.12,"dewPoint":50.78,"humidity":0.4,"windSpeed":15.5,"windBearing":279,"visibility":10,"cloudCover":0.38,"pressure":998.1},{"time":1145142000,"summary":"Clear","icon":"clear-day","precipIntensity":0,"precipProbability":0,"temperature":76.36,"apparentTemperature":76.36,"dewPoint":50.51,"humidity":0.4,"windSpeed":11.94,"windBearing":279,"visibility":10,"cloudCover":0.12,"pressure":998.59},{"time":1145145600,"summary":"Partly Cloudy","icon":"partly-cloudy-night","precipIntensity":0,"precipProbability":0,"temperature":66.11,"apparentTemperature":66.11,"dewPoint":31.06,"humidity":0.27,"windSpeed":5.61,"windBearing":349,"visibility":10,"cloudCover":0.29,"pressure":1004.4},{"time":1145149200,"summary":"Clear","icon":"clear-night","precipIntensity":0,"precipProbability":0,"temperature":70.81,"apparentTemperature":70.81,"dewPoint":51.7,"humidity":0.51,"windSpeed":5.22,"windBearing":267,"visibility":10,"cloudCover":0.24,"pressure":999.9},{"time":1145152800,"summary":"Clear","icon":"clear-night","precipIntensity":0,"precipProbability":0,"temperature":68.93,"apparentTemperature":68.93,"dewPoint":45.44,"humidity":0.43,"windSpeed":5.79,"windBearing":323,"visibility":10,"cloudCover":0.17,"pressure":1001.31},{"time":1145156400,"summary":"Clear","icon":"clear-night","precipIntensity":0,"precipProbability":0,"temperature":65.53,"apparentTemperature":65.53,"dewPoint":36.68,"humidity":0.34,"windSpeed":8.57,"windBearing":337,"visibility":10,"cloudCover":0,"pressure":1002.27}]},"daily":{"data":[{"time":1145073600,"summary":"Partly cloudy until evening.","icon":"partly-cloudy-day","sunriseTime":1145096628,"sunsetTime":1145144379,"moonPhase":0.56,"precipIntensity":0.0001,"precipIntensityMax":0.002,"precipIntensityMaxTime":1145098800,"precipProbability":0.2,"precipType":"rain","temperatureMin":54.46,"temperatureMinTime":1145080800,"temperatureMax":78.71,"temperatureMaxTime":1145131200,"apparentTemperatureMin":54.46,"apparentTemperatureMinTime":1145080800,"apparentTemperatureMax":78.71,"apparentTemperatureMaxTime":1145131200,"dewPoint":51.43,"humidity":0.63,"windSpeed":7.92,"windBearing":272,"visibility":8.14,"cloudCover":0.47,"pressure":1000.71}]},"flags":{"sources":["isd"],"isd-stations":["720304-64752","724074-93780","724080-13739","724085-94732","997286-99999"],"units":"us"}}