{"latitude":39.952247,"longitude":-75.163894,"timezone":"America/New_York","offset":-4,"currently":{"time":1251590400,"summary":"Clear","icon":"clear-night","precipIntensity":0,"precipProbability":0,"temperature":74.37,"apparentTemperature":74.37,"dewPoint":55.05,"humidity":0.51,"windSpeed":7.87,"windBearing":310,"visibility":10,"cloudCover":0.15,"pressure":1011.79},"hourly":{"summary":"Heavy rain overnight.","icon":"rain","data":[{"time":1251518400,"summary":"Overcast","icon":"cloudy","precipIntensity":0.0027,"precipProbability":0.27,"precipType":"rain","temperature":69.62,"apparentTemperature":69.62,"dewPoint":67.85,"humidity":0.94,"windSpeed":2.89,"windBearing":75,"visibility":6.1,"cloudCover":1,"pressure":1014.83},{"time":1251522000,"summary":"Overcast","icon":"cloudy","precipIntensity":0.0027,"precipProbability":0.27,"precipType":"rain","temperature":70.55,"apparentTemperature":70.55,"dewPoint":68.53,"humidity":0.93,"windSpeed":1.08,"windBearing":20,"visibility":4.99,"cloudCover":1,"pressure":1013.78},{"time":1251525600,"summary":"Overcast","icon":"cloudy","precipIntensity":0,"precipProbability":0,"temperature":70.2,"apparentTemperature":70.2,"dewPoint":68.19,"humidity":0.93,"windSpeed":2.99,"windBearing":73,"visibility":4.86,"cloudCover":1,"pressure":1013.1},{"time":1251529200,"summary":"Light Rain","icon":"rain","precipIntensity":0.0447,"precipProbability":0.64,"precipType":"rain","temperature":70.55,"apparentTemperature":70.55,"dewPoint":68.53,"humidity":0.93,"windSpeed":4.73,"windBearing":93,"visibility":4.04,"cloudCover":1,"pressure":1012.38},{"time":1251532800,"summary":"Light Rain","icon":"rain","precipIntensity":0.0383,"precipProbability":0.64,"precipType":"rain","temperature":70.75,"apparentTemperature":70.75,"dewPoint":68.72,"humidity":0.93,"windSpeed":4.66,"windBearing":79,"visibility":7.62,"cloudCover":0.93,"pressure":1011.55},{"time":1251536400,"summary":"Overcast","icon":"cloudy","precipIntensity":0,"precipProbability":0,"temperature":70.67,"apparentTemperature":70.67,"dewPoint":69.47,"humidity":0.96,"windSpeed":3.46,"windBearing":89,"visibility":7.95,"cloudCover":1,"pressure":1010.61},{"time":1251540000,"summary":"Mostly Cloudy","icon":"partly-cloudy-night","precipIntensity":0,"precipProbability":0,"temperature":70.95,"apparentTemperature":70.95,"dewPoint":69.17,"humidity":0.94,"windSpeed":4.35,"windBearing":79,"visibility":8.63,"cloudCover":0.88,"pressure":1010.06},{"time":1251543600,"summary":"Overcast","icon":"cloudy","precipIntensity":0,"precipProbability":0,"temperature":71.61,"apparentTemperature":71.61,"dewPoint":69.57,"humidity":0.93,"windSpeed":4.35,"windBearing":95,"visibility":8.08,"cloudCover":1,"pressure":1010.32},{"time":1251547200,"summary":"Drizzle","icon":"rain","precipIntensity":0.0054,"precipProbability":0.54,"precipType":"rain","temperature":71.8,"apparentTemperature":71.8,"dewPoint":70.01,"humidity":0.94,"windSpeed":3.15,"windBearing":30,"visibility":8.63,"cloudCover":1,"pressure":1009.67},{"time":1251550800,"summary":"Overcast","icon":"cloudy","precipIntensity":0,"precipProbability":0,"temperature":72.8,"apparentTemperature":72.8,"dewPoint":70.57,"humidity":0.93,"windSpeed":4.75,"windBearing":42,"visibility":10,"cloudCover":1,"pressure":1008.4},{"time":1251554400,"summary":"Overcast","icon":"cloudy","precipIntensity":0,"precipProbability":0,"temperature":73.53,"apparentTemperature":73.53,"dewPoint":70.52,"humidity":0.9,"windSpeed":5.28,"windBearing":58,"visibility":10,"cloudCover":1,"pressure":1007.71},{"time":1251558000,"summary":"Overcast","icon":"cloudy","precipIntensity":0,"precipProbability":0,"temperature":74.74,"apparentTemperature":74.74,"dewPoint":71.44,"humidity":0.9,"windSpeed":0,"visibility":9.76,"cloudCover":1,"pressure":1007.98},{"time":1251561600,"summary":"Overcast","icon":"cloudy","precipIntensity":0,"precipProbability":0,"temperature":76.39,"apparentTemperature":76.39,"dewPoint":71.54,"humidity":0.85,"windSpeed":3,"windBearing":340,"visibility":10,"cloudCover":1,"pressure":1007.37},{"time":1251565200,"summary":"Mostly Cloudy","icon":"partly-cloudy-day","precipIntensity":0,"precipProbability":0,"temperature":80.26,"apparentTemperature":84.11,"dewPoint":71.74,"humidity":0.75,"windSpeed":1.53,"windBearing":270,"visibility":10,"cloudCover":0.75,"pressure":1006.73},{"time":1251568800,"summary":"Mostly Cloudy","icon":"partly-cloudy-day","precipIntensity":0,"precipProbability":0,"temperature":80.46,"apparentTemperature":83.88,"dewPoint":70.27,"humidity":0.71,"windSpeed":6,"windBearing":300,"visibility":10,"cloudCover":0.64,"pressure":1006.03},{"time":1251572400,"summary":"Mostly Cloudy","icon":"partly-cloudy-day","precipIntensity":0,"precipProbability":0,"temperature":82.41,"apparentTemperature":86.37,"dewPoint":70.05,"humidity":0.66,"windSpeed":4.71,"windBearing":243,"visibility":10,"cloudCover":0.7,"pressure":1005.68},{"time":1251576000,"summary":"Mostly Cloudy","icon":"partly-cloudy-day","precipIntensity":0,"precipProbability":0,"temperature":83.47,"apparentTemperature":88.06,"dewPoint":70.64,"humidity":0.65,"windSpeed":1.47,"windBearing":240,"visibility":10,"cloudCover":0.63,"pressure":1005.63},{"time":1251579600,"summary":"Partly Cloudy","icon":"partly-cloudy-day","precipIntensity":0.0027,"precipProbability":0.27,"precipType":"rain","temperature":82.78,"apparentTemperature":87.28,"dewPoint":70.83,"humidity":0.67,"windSpeed":3.37,"windBearing":240,"visibility":8.63,"cloudCover":0.55,"pressure":1005.42},{"time":1251583200,"summary":"Drizzle","icon":"rain","precipIntensity":0.0082,"precipProbability":0.27,"precipType":"rain","temperature":78.94,"apparentTemperature":78.94,"dewPoint":72.81,"humidity":0.82,"windSpeed":4.26,"windBearing":200,"visibility":6.86,"cloudCover":0.61,"pressure":1005.52},{"time":1251586800,"summary":"Rain","icon":"rain","precipIntensity":0.0839,"precipProbability":1,"precipType":"rain","temperature":75.61,"apparentTemperature":75.61,"dewPoint":71.61,"humidity":0.87,"windSpeed":3.15,"windBearing":200,"visibility":9.18,"cloudCover":0.43,"pressure":1006.15},{"time":1251590400,"summary":"Clear","icon":"clear-night","precipIntensity":0,"precipProbability":0,"temperature":74.37,"apparentTemperature":74.37,"dewPoint":55.05,"humidity":0.51,"windSpeed":7.87,"windBearing":310,"visibility":10,"cloudCover":0.15,"pressure":1011.79},{"time":1251594000,"summary":"Mostly Cloudy","icon":"partly-cloudy-night","precipIntensity":0.0027,"precipProbability":0.27,"precipType":"rain","temperature":74.03,"apparentTemperature":74.03,"dewPoint":70.13,"humidity":0.88,"windSpeed":1.03,"windBearing":224,"visibility":9.76,"cloudCover":0.62,"pressure":1007.18},{"time":1251597600,"summary":"Light Rain","icon":"rain","precipIntensity":0.0185,"precipProbability":0.54,"precipType":"rain","temperature":72.83,"apparentTemperature":72.83,"dewPoint":67.86,"humidity":0.84,"windSpeed":12.57,"windBearing":343,"visibility":5.73,"cloudCover":0.88,"pressure":1008.37},{"time":1251601200,"summary":"Heavy Rain","icon":"rain","precipIntensity":0.3516,"precipProbability":1,"precipType":"rain","temperature":69.47,"apparentTemperature":69.47,"dewPoint":66.32,"humidity":0.9,"windSpeed":0.87,"windBearing":32,"visibility":4.67,"cloudCover":0.93,"pressure":1009.26}]},"daily":{"data":[{"time":1251518400,"summary":"Heavy rain in the evening.","icon":"rain","sunriseTime":1251541644,"sunsetTime":1251589116,"moonPhase":0.32,"precipIntensity":0.0234,"precipIntensityMax":0.3516,"precipIntensityMaxTime":1251601200,"precipProbability":1,"precipType":"rain","temperatureMin":69.47,"temperatureMinTime":1251601200,"temperatureMax":83.47,"temperatureMaxTime":1251576000,"apparentTemperatureMin":69.47,"apparentTemperatureMinTime":1251601200,"apparentTemperatureMax":88.06,"apparentTemperatureMaxTime":1251576000,"dewPoint":69.23,"humidity":0.85,"windSpeed":1.07,"windBearing":18,"visibility":8.15,"cloudCover":0.82,"pressure":1008.98}]},"flags":{"sources":["isd"],"isd-stations":["720304-64752","724080-13739","724085-94732","997286-99999","998265-99999"],"units":"us"}}